{"stat.walkOneCm":491847,"stat.playerKills":35,"achievement.openInventory":22,"stat.leaveGame":4,"stat.damageTaken":6774,"stat.useItem.minecraft.diamond_sword":40,"stat.useItem.minecraft.potion":25,"stat.flyOneCm":764760,"stat.deaths":8,"stat.jump":3055,"stat.swimOneCm":5677,"stat.playOneMinute":55698,"stat.fallOneCm":77639,"stat.climbOneCm":901,"stat.useItem.minecraft.wooden_sword":172,"stat.useItem.minecraft.stone_sword":164,"stat.damageDealt":25965,"stat.crouchOneCm":5537,"stat.timeSinceDeath":1888,"stat.sprintOneCm":354976,"achievement.exploreAllBiomes":{"value":0,"progress":["Plains"]},"stat.diveOneCm":201}